trojai_rl/__init__.py
trojai_rl/datagen/__init__.py
trojai_rl/datagen/environment_factory.py
trojai_rl/datagen/envs/wrapped_boxing.py
trojai_rl/modelgen/__init__.py
trojai_rl/modelgen/config.py
trojai_rl/modelgen/optimizer_interface.py
trojai_rl/modelgen/runner.py
trojai_rl/modelgen/stable_baselines_optimizer.py
trojai_rl/modelgen/statistics.py
trojai_rl/modelgen/torch_ac_optimizer.py
trojai_rl/modelgen/utils.py
trojai_rl/modelgen/architectures/atari_architectures.py
trojai_rl/modelgen/architectures/minigrid_architectures.py
trojai_rl/modelgen/architectures/minigrid_stable_baselines.py
trojai_rl-0.1.1.data/scripts/wrapped_boxing.py
trojai_rl-0.1.1.dist-info/LICENSE
trojai_rl-0.1.1.dist-info/METADATA
trojai_rl-0.1.1.dist-info/WHEEL
trojai_rl-0.1.1.dist-info/top_level.txt
trojai_rl-0.1.1.dist-info/RECORD
