Metadata-Version: 2.1
Name: trojai-rl
Version: 0.1.1
Summary: TrojAI RL model generation library
Home-page: https://github.com/trojai/trojai_rl
Author: Chace Ashcraft Kiran Karra
Author-email: chace.ashcraft@jhuapl.edu, kiran.karra@jhuapl.edu
License: Apache License 2.0
Keywords: reinforcement-learning trojan adversarial
Platform: UNKNOWN
Classifier: Development Status :: 3 - Alpha
Classifier: Intended Audience :: Developers
Classifier: Intended Audience :: Science/Research
Classifier: Topic :: Scientific/Engineering
Classifier: Topic :: Scientific/Engineering :: Artificial Intelligence
Classifier: License :: OSI Approved :: Apache Software License
Classifier: Programming Language :: Python :: 3 :: Only
Requires-Python: >=3.7
Requires-Dist: numpy (==1.17.4)
Requires-Dist: tqdm (>=4.32.1)
Requires-Dist: torch (>=1.4.0)
Requires-Dist: torch-ac (==1.1.0)
Requires-Dist: gym (==0.15.3)
Requires-Dist: atari-py (~=0.2.0)
Requires-Dist: opencv-python
Provides-Extra: stable_baselines
Requires-Dist: stable-baselines (==2.8.0) ; extra == 'stable_baselines'
Requires-Dist: tensorflow-gpu (==1.14) ; (platform_system == "Linux") and extra == 'stable_baselines'
Requires-Dist: tensorflow-gpu (==1.14) ; (platform_system == "Windows") and extra == 'stable_baselines'
Requires-Dist: tensorflow (==1.14) ; (sys_platform == "darwin") and extra == 'stable_baselines'
Provides-Extra: test
Requires-Dist: nose ; extra == 'test'
